Metadata-Version: 1.0
Name: gaus-bino-disto
Version: 0.1.1
Summary: Gaussian and Binomial distributions
Home-page: UNKNOWN
Author: Erol SEN
Author-email: ierolsen@outlook.com
License: UNKNOWN
Platform: UNKNOWN
